musterai/__init__.py
musterai/agent.py
musterai/muster.py
musterai/process.py
musterai/prompts.py
musterai/task.py
musterai/agent_monitors/__init__.py
musterai/agent_monitors/agent_monitor.py
musterai/agents/__init__.py
musterai/agents/agent_vote.py
musterai/agents/cache_handler.py
musterai/agents/output_parser.py
musterai/agents/tools_handler.py
musterai/memory/__init__.py
musterai/memory/long_term_memory/__init__.py
musterai/memory/long_term_memory/ltmsqlite.py
musterai/tools/__init__.py
musterai/tools/agent_tools.py
musterai-1.0.7.dist-info/METADATA
musterai-1.0.7.dist-info/WHEEL
musterai-1.0.7.dist-info/top_level.txt
musterai-1.0.7.dist-info/RECORD
